Workbook

Sheet Projeto
A3: PROJETO DO POÇO

Sheet Perfuração Cardwell
C2: CUSTEIO PERFURAÇÃO
C3: CARDWELL (24h) - 3 equipes 14x7
A6: LEGENDA | D6: DADOS | G6: POÇO | I6: DESLOCAMENTOS | L6: FONTE | M6: NOTAS
B7: Células a serem preenchidas, conforme projeto/internamente | C7: Cliente: | D7: SANEPAR | F7: Prof. (m) | G7: 870 | I7: Campinas (km) | J7: 440 | L7: RotaMapas | M7: Base de saída dos transportes x Obra
B8: Responsabilidades Contratante/Contratada | C8: Município: | D8: Cornélio Procópio/PR | F8: N.E. (m) | I8: São Paulo (km) | J8: 464 | L8: RotaMapas | M8: Base de saída de equipe de perfuração x Obra
A9: - | B9: Itens direcionados ao Faturamento Direto/Preço de venda dos materiais | C9: Endereço: | D9: Rua dos Expedicionários S/N | F9: N.D. (m) | G9: 280 | I9: Araraquara (km) | J9: 337 | L9: RotaMapas | M9: Galpão (DH) x obra
A10: - | B10: Preço de venda do poço | F10: Q (m³/h) | G10: 300 | I10: Jundiaí (km) | J10: 439 | L10: RotaMapas | M10: Perfil Master (perfilagem) x obra
C11: PRAZO OBRA | D11: =$I$42 -> 100 | F11: S (m) | I11: Ribeirão Bonito (km) | J11: 325 | L11: RotaMapas | M11: Locavem (compressor) x obra
A13: CRONOGRAMA ESTIMADO
A14: ITEM | B14: 1. SERVIÇOS | I14: DIAS (3 EQUIPES) | J14: OPERAÇÃO SONDA
A15: 1.1 | B15: DTM (mobilização e desmobilização) - cada operação em média 6 horas | I15: 8 | L15: Estimado | M15: Dias de DTM deve ser pactuado com operação, a depender da distância de deslocamento. Considera-se em média de 3 a 5 dias.
A16: 1.2 | B16: Instalação do Canteiro de Obras, Tanques de Lama, Canaletas, etc. | I16: 5 | L16: Estimado | M16: 5 dias em média para instalação do canteiro
A17: METODOLOGIA | C17: Ø" Perfuração | D17: Ø" Revestimento | E17: Metragem inicial | F17: Metragem final | G17: Metragem total | H17: Avanço | L17: Estimado
A18: 1.3 | B18: Perfuração Solo Sedimentos - Rotativa | C18: 26 | D18: 20 | E18: 0 | F18: 11.5 | G18: =F18-E18 -> 11.5 | H18: 10 | I18: =ROUNDUP(G18/H18,0) -> 2 | J18: =I18 -> 2 | L18: Estimado
A19: 1.4 | B19: Instalação do Tubo de Boca | C19: =$C$18 -> 26 | D19: =$D$18 -> 20 | E19: =$E$18 -> 0 | F19: =$F$18 -> 11.5 | G19: =F19-E19 -> 11.5 | H19: 10 | I19: =ROUNDUP(G19/H19,0) -> 2 | J19: =I19 -> 2 | L19: Estimado
A20: 1.5 | B20: Cimentação do Tubo de Boca e Cura | C20: =$C$18 -> 26 | D20: =E18 -> 0 | E20: =$E$19 -> 0 | F20: =$F$19 -> 11.5 | G20: =F20-E20 -> 11.5 | H20: 10 | I20: =ROUNDUP(G20/H20,0) -> 2 | J20: =I20 -> 2 | L20: Estimado
A21: 1.6 | B21: Perfuração Basalto - Rotopneumática | C21: 18 | D21: 14 | E21: =$F$18 -> 11.5 | F21: 150 | G21: =F21-E21 -> 138.5 | H21: 50 | I21: =ROUNDUP(G21/H21,0) -> 3 | J21: =I21 -> 3 | L21: Estimado | M21: Geralmente utilizamos Rotopneumático quando o tubo de boca é instalado em profundidades "rasas". A partir de 70 metros é possível considerar o método rotativo, porém necessário pactuar com operações. Para roto, faz-se ideal considerar até 150m para não ultrapassar a efetividade da sonda. Para 18" pode-se considerar 50 metros por dia.
A22: 1.7 | B22: Manobra troca do sistema de perfuração (broca) | I22: 1 | J22: =I22 -> 1 | L22: Estimado
A23: 1.8 | B23: Perfuração Basalto - Rotativa | C23: 17.5 | D23: 14 | E23: =$F$21 -> 150 | F23: 400 | G23: =F23-E23 -> 250 | H23: 15 | I23: =ROUNDUP(G23/H23,0) -> 17 | J23: =I23 -> 17 | L23: Estimado | M23: Pactuar com operações. Para 17 1/2" pode-se considerar 15 metros.
A24: 1.8 | B24: Perfuração Basalto - Rotativa | C24: 17.5 | D24: 10 | E24: =F23 -> 400 | F24: 750 | G24: =F24-E24 -> 350 | H24: 15 | I24: =ROUNDUP(G24/H24,0) -> 24 | J24: =I24 -> 24 | L24: Estimado | M24: Pactuar com operações. Para 17 1/2" pode-se considerar 15 metros.
A25: 1.9 | B25: Manobra troca do sistema de perfuração + preparação do fluido à base de CMC | I25: 1 | J25: =I25 -> 1 | L25: Estimado
A26: 1.10 | B26: Perfuração Arenito - Rotativa | C26: 17.5 | D26: 8 | E26: =F24 -> 750 | F26: 870 | G26: =F26-E26 -> 120 | H26: 35 | I26: =ROUNDUP(G26/H26,0) -> 4 | J26: =I26 -> 4 | L26: Estimado | M26: Pactuar com operações. Para perfuração em 17 1/2" pode considerar 50 metros por dia.
A27: 1.11 | B27: Perfilagem Geofísica (Multi-Função + Sônico) | I27: 1 | J27: =I27 -> 1 | L27: Estimado | M27: Sempre pactuar a necessidade de separar em duas corridas a Perfilagem Geofísica, caso houver Reabertura.
A28: 1.12 | B28: Manobra troca do sistema de perfuração (broca) | I28: 1 | J28: =I28 -> 1 | L28: Estimado
A29: 1.13 | B29: Perfuração Arenito (REABERTURA) - Rotativa | C29: 20 | D29: 8 | E29: =E26 -> 750 | F29: =F26 -> 870 | G29: =F29-E29 -> 120 | H29: 30 | I29: =ROUNDUP(G29/H29,0) -> 4 | J29: =I29 -> 4 | L29: Estimado
A30: 1.14 | B30: Perfilagem Geofísica (Cáliper + Inclinação) | I30: 1 | J30: =I30 -> 1 | L30: Estimado | M30: Sempre pactuar a necessidade de separar em duas corridas de Perfilagem Geofísica, caso houver Reabertura.
A31: 1.15 | B31: Condicionamento da Lama | I31: 1 | J31: =I31 -> 1 | L31: Estimado | M31: Em média 1,0 a 1,5 dia. Pactuar internamente ou basear em projeto, caso houver.
A32: 1.16 | B32: Descida do Revestimento | E32: 0 | F32: =$G$7 -> 870 | G32: =F32-E32 -> 870 | H32: 400 | I32: =ROUNDUP(G32/H32,0) -> 3 | J32: =I32 -> 3 | L32: Estimado | M32: Em média 1,0 a 1,5 dia. Pactuar internamente ou basear em projeto, caso houver.
A33: 1.17 | B33: Descida e condicionamento do Pré-Filtro | E33: 0 | F33: =$G$7 -> 870 | G33: =F33-E33 -> 870 | H33: 400 | I33: =ROUNDUP(G33/H33,0) -> 3 | J33: =I33 -> 3 | L33: Estimado | M33: Em média 2 bags de pré-filtro por hora
A34: 1.18 | B34: Instalação e retirada do Air-Lift | E34: Metragem Total | G34: =$G$7 -> 870 | H34: 870 | I34: =ROUNDUP(G34/H34,0) -> 1 | J34: =I34 -> 1 | L34: Estimado | N34: Considerar a metragem total do poço.
A35: 1.19 | B35: Desenvolvimento - Sistema Air-lift (12 horas/dia) | E35: Quantidade de horas | G35: 24 | H35: 10 | I35: =ROUNDUP(G35/H35,0) -> 3 | J35: =I35 -> 3 | L35: Estimado | M35: Considera-se avanço de 10h devido a duração/dia de funcionamento ideal do compressor.
A36: 1.20 | B36: Instalação e retirada do conjunto moto-bomba | E36: Profundidade de instalação | G36: =IF($G$9>0,$G$9+ 20, 0.7*$G$7) -> 300 | H36: 300 | I36: =G36/H36 -> 1 | J36: =I36 -> 1 | L36: Estimado | M36: Normalmente considera-se 1 dia a instalação do conjunto motobomba. Pactuar internamente ou basear em projeto, caso houver.
A37: 1.21 | B37: Desenvolvimento - Bomba submersa | E37: Quantidade de horas | G37: 24 | H37: 24 | I37: =ROUNDUP(G37/H37,1) -> 1 | J37: =I37 -> 1 | L37: Estimado
A38: 1.22 | B38: Teste de Vazão | E38: Quantidade de horas | G38: 100 | H38: 24 | I38: =ROUNDUP(G38/H38,1) -> 4.2 | J38: =I38 -> 4.2 | L38: Estimado
A39: 1.23 | B39: Perfilagem Óptica | I39: 1 | J39: =I39 -> 1 | L39: Estimado
A40: 1.24 | B40: Desmontagem da Sonda | I40: =I16 -> 5 | J40: =I40 -> 5 | L40: Estimado
A41: 1.25 | B41: DSR - Descanso aos Domingos (Sim:1 Não:0) | G41: (Sim:1 Não:0) | H41: 0 | I41: =ROUNDUP(SUM(I16,I18:I40)/6,0)*H41 -> 0 | J41: =I41 -> 0 | L41: Estimado
A42: SUBTOTAL | B42: PRAZOS (DIAS) | I42: =ROUNDUP(SUM(I15:I16,I18:I41),0) -> 100 | J42: =SUM(J16:J41) -> 86.2
A44: ITEM | B44: 2. TRANSPORTES | L44: FONTE | M44: NOTAS
B45: Mobilização | C45: Equipamento | D45: Capacidade | E45: Saída | F45: Município de referência | H45: Viagens | I45: Frete unitário | J45: Custo Total
A46: 2.1 | B46: Reboque Sonda CARDWELL - Cavalo Trucado | C46: Cavalo Trucado | E46: Campinas/SP | F46: =D8 -> Cornélio Procópio/PR | H46: 1 | I46: 10080.35 | J46: =I46*H46 -> 10080.35 | L46: Planilha de Preços de Frete
A47: 2.2 | B47: Reboque Bomba EMSCO - Cavalo Toco | C47: Cavalo Toco | D47: 25 | E47: Campinas/SP | F47: =F46 -> Cornélio Procópio/PR | H47: 1 | I47: 7754.12 | J47: =I47*H47 -> 7754.12 | L47: Planilha de Preços de frete | M47: Normalmente utiliza-se tanto a bomba EMSCO quanto VULCAN para perfuração de poços profundos. Para poços mais rasos, apenas VULCAN.
A48: 2.3 | B48: Bomba VULCAN - Carreta | C48: Carreta | D48: 30 | E48: Campinas/SP | F48: =F46 -> Cornélio Procópio/PR | H48: 1 | I48: =I47 -> 7754.12 | J48: =I48*H48 -> 7754.12 | L48: Planilha de Preços de frete | M48: Normalmente utiliza-se tanto a bomba EMSCO quanto VULCAN para perfuração de poços profundos. Para poços mais rasos, apenas VULCAN.
A49: 2.4 | B49: Acessórios e Equipamentos | C49: Carreta | D49: 30 | E49: Campinas/SP | F49: =F46 -> Cornélio Procópio/PR | H49: 6 | I49: =I48 -> 7754.12 | J49: =I49*H49 -> 46524.72 | L49: Planilha de Preços de frete | M49: O número de viagens das carretas pode ser alterado, conforme distância de deslocamento e complexidade do poço.
A50: 2.5 | B50: Deslocamento | C50: Caminhão Munck | E50: São Paulo/SP | F50: =F46 -> Cornélio Procópio/PR | H50: 1 | I50: 948.97 | J50: =I50*H50 -> 948.97 | L50: Qualp | M50: Qualp - Cálculo de rotas com pedágio, combustível, distância e tempo/ Munck - 4 eixos
A51: 2.6 | B51: Acessórios Diversos | C51: Caminhão Truck | D51: 12 | E51: Campinas/SP | F51: =F46 -> Cornélio Procópio/PR | H51: 2 | I51: 4431.53 | J51: =I51*H51 -> 8863.06 | L51: Planilha de Preços de frete
A52: 2.7 | B52: Consumíveis para fluido de perfuração | C52: Carreta | D52: 30 | E52: Campinas/SP | F52: =F46 -> Cornélio Procópio/PR | H52: 2 | I52: =I49 -> 7754.12 | J52: =I52*H52 -> 15508.24 | L52: Planilha de Preços de frete
B53: Desmobilização | C53: Equipamento | D53: Capacidade | E53: Saída | F53: =F45 -> Município de referência | H53: Viagens | I53: Frete unitário | J53: Custo Total
A54: 2.7 | B54: Reboque Sonda CARDWELL - Cavalo Trucado | C54: Cavalo Trucado | E54: =F46 -> Cornélio Procópio/PR | F54: =E46 -> Campinas/SP | H54: 1 | I54: =I46 -> 10080.35 | J54: =I54*H54 -> 10080.35 | L54: Planilha de Preços de Frete
A55: 2.8 | B55: Reboque Bomba EMSCO - Cavalo Toco | C55: Cavalo Toco | D55: 25 | E55: =F47 -> Cornélio Procópio/PR | F55: =E47 -> Campinas/SP | H55: 1 | I55: =I47 -> 7754.12 | J55: =I55*H55 -> 7754.12 | L55: Planilha de Preços de Frete | M55: Normalmente utilizam-se tanto a bomba EMSCO quanto VULCAN para perfuração de poços profundos. Para poços mais rasos, apenas VULCAN.
A56: 2.9 | B56: Bomba VULCAN - Carreta | C56: Carreta | D56: 30 | E56: =F48 -> Cornélio Procópio/PR | F56: =E48 -> Campinas/SP | H56: 1 | I56: =I48 -> 7754.12 | J56: =I56*H56 -> 7754.12 | L56: Planilha de Preços de Frete | M56: Normalmente utilizam-se tanto a bomba EMSCO quanto VULCAN para perfuração de poços profundos. Para poços mais rasos, apenas VULCAN.
A57: 2.10 | B57: Acessórios e Equipamentos | C57: Carreta | D57: 30 | E57: =F49 -> Cornélio Procópio/PR | F57: =E49 -> Campinas/SP | H57: 6 | I57: =I49 -> 7754.12 | J57: =I57*H57 -> 46524.72 | L57: Planilha de Preços de Frete | M57: O número de viagens das carretas pode ser alterado, conforme distância de deslocamento. Normalmente considera-se 6 viagens.
B58: Revestimento | C58: Equipamento | D58: Capacidade | E58: Saída | F58: Município de referência | G58: Peso | H58: Viagens | I58: Frete unitário | J58: Custo Total
A59: 2.11 | B59: Filtros | C59: Caminhão Truck | D59: 13 | E59: Sorocaba/SP | F59: =F46 -> Cornélio Procópio/PR | G59: =$F$159/1000 -> 3.33 | H59: =ROUNDUP($G$59/$D$59,0) -> 1 | I59: 4012.5 | J59: =I59*H59 -> 4012.5 | L59: Planilha de Preços de Frete | M59: Frete Sorocaba-Araraquara padrão, quando filtro super-weld com rosca. Frete Sorocaba-Obra, demais filtros com ou sem rosca.
A60: 2.12 | B60: Revestimento | C60: Carreta | D60: 30 | E60: Araraquara/SP | F60: =F46 -> Cornélio Procópio/PR | G60: =SUM($F$155:$F$158)/1000 -> 55.028487 | H60: =ROUNDUP($G$60/$D$60,0) -> 2 | I60: 5440.84 | J60: =I60*H60 -> 10881.68 | L60: Planilha de Preços de Frete | M60: Se o revestimento tiver rosca, considerar a saída de Araraquara. Caso não tenha rosca, o fornecedor deverá entregar o revestimento na obra. Em caso de obras que não sejam no estado de SP, verificar as condições de entrega do fornecedor.
A61: 2.13 | B61: Pré-Filtro | C61: Carreta | D61: 30 | E61: Descalvado/SP | F61: =F46 -> Cornélio Procópio/PR | G61: =$H$163 -> 123 | H61: =ROUNDUP($G$61/$D$61,0) -> 5 | I61: 6884.33 | J61: =I61*H61 -> 34421.65 | L61: Planilha de Preços de Frete | M61: Fornecedor habitual Areia Itaporanga
A62: 2.14 | B62: Ponteiras | C62: Caminhão Truck | D62: 13 | E62: Araraquara/SP | F62: Sorocaba/SP | H62: 1 | I62: 2710 | J62: =I62*H62 -> 2710 | L62: Planilha de Preços de Frete | M62: Haverá ponteira apenas se houver rosca, exceto filtro do tipo super-weld. Frete unitário Araraquara-Sorocaba padrão = R$ 2.710,00 TRUCK
B63: Compressor (Locavem) | D63: Frete (R$/KM) | E63: Km (ida e volta) | F63: Município de referência | G63: Quantidade | H63: Estadia | I63: Frete unitário | J63: Custo Total
A64: 2.15 | B64: Compressor 950 pcm X 350 psi (Perfuração) - Ida e volta | D64: 6.5 | E64: =$J$10*2 -> 878 | F64: Jundiaí/SP | G64: 1 | H64: =IF($E$64<=1000,0,IF($E$64>1000,($E$64/1000)*200)) -> 0 | I64: =($D$64*$E$64)+$H$64 -> 5707 | J64: =I64*G64 -> 5707 | L64: Locavem | M64: Locação dos compressores - Jundiaí x Obra. Considerar 2 compressores para a perfuração apenas se houver rotopneumática.
B65: Veículos | D65: Gasolina (R$/L) | E65: Pedágio/km | F65: Município de referência | G65: Quantidade | H65: Rendimento | I65: Custo/km | J65: Custo Total
A66: 2.17 | B66: Equipes - Ida e volta | F66: Marília/SP | G66: 2 | I66: 180 | J66: =G66*I66*9 -> 3240 | L66: Quero Passagem | M66: Buscar o custo da passagem de Marília x Obra (município mais próximo) e preencher na célula I64. Referenciar município na célula F64
A67: 2.18 | B67: Veículo Strada/Montana - Ida e volta | D67: 5.8 | E67: 0.5 | F67: São Paulo/SP | G67: 1 | H67: 10 | I67: =E67+(D67/H67) -> 1.08 | J67: =G67*I67*J9*2 -> 727.92 | L67: Gasolina - Petrobras | M67: Procurar valor da gasolina na região - Petrobras
A68: 2.19 | B68: Veículo Básico - Geólogo - Ida e volta | D68: =$D$67 -> 5.8 | E68: 0.5 | F68: São Paulo/SP | G68: =ROUNDUP(I76/15,0) -> 4 | H68: 10 | I68: =E68+(D68/H68) -> 1.08 | J68: =G68*I68*J9*2 -> 2911.68 | L68: Gasolina - Petrobras | M68: Procurar valor da gasolina na região - Petrobras
A69: 2.20 | B69: Veículo Básico - Supervisor de Segurança - Ida e volta | D69: =$D$67 -> 5.8 | E69: 0.5 | F69: São Paulo/SP | G69: =ROUNDUP(I77/15,0) -> 7 | H69: 10 | I69: =E69+(D69/H69) -> 1.08 | J69: =G69*I69*J9*2 -> 5095.44 | L69: Gasolina - Petrobras | M69: Procurar valor da gasolina na região - Petrobras
A70: 2.21 | B70: Veículo Básico - Coordenador - Ida e volta | D70: =$D$67 -> 5.8 | E70: 0.5 | F70: São Paulo/SP | G70: =ROUNDUP(I79/15,0) -> 7 | H70: 10 | I70: =E70+(D70/H70) -> 1.08 | J70: =G70*I70*J8*2 -> 7015.68 | L70: Gasolina - Petrobras | M70: Procurar valor da gasolina na região - Petrobras
A71: 2.22 | B71: Trocas de Equipes - Mês | F71: Marília/SP | G71: =ROUNDDOWN((D11-7)/7,0) -> 13 | I71: =$I$66 -> 180 | J71: =G71*I71*9 -> 21060
A72: SUBTOTAL | B72: SUBTOTAL TRANSPORTES | J72: =SUM(J46:J71) -> 267330.44
A74: ITEM | B74: 3. MÃO DE OBRA | L74: FONTE | M74: NOTAS
B75: Função | F75: Salário/dia | G75: Presença (%) | H75: Total dia útil | I75: Total de dias na obra | J75: Custo Total
A76: 3.1 | B76: Geólogo I | F76: 805.34 | G76: 0.5 | H76: =$D$11 -> 100 | I76: =ROUNDUP(G76*H76,0) -> 50 | J76: =F76*I76 -> 40267 | L76: Planilha HH | M76: 60% habitualmente, caso haja exigência do cliente de presença full-time, considerar 100%.
A77: 3.4 | B77: Técnico Segurança Trabalho Jr. | F77: 514.8436 | G77: 1 | H77: =$D$11 -> 100 | I77: =ROUNDUP(G77*H77,0) -> 100 | J77: =F77*I77 -> 51484.36 | L77: Planilha HH
A78: 3.5 | B78: Soldador | F78: 470.35661 | G78: 0.1 | H78: =$D$11 -> 100 | I78: =ROUNDUP(G78*H78,0) -> 10 | J78: =F78*I78 -> 4703.5661 | L78: Planilha HH
A79: 3.6 | B79: Coordenador de Obra | F79: 1102.4889 | G79: 1 | H79: =$D$11 -> 100 | I79: =ROUNDUP(G79*H79,0) -> 100 | J79: =F79*I79 -> 110248.89 | L79: Planilha HH | O79: 1416
A80: 3.7 | B80: Encarregado de Manutenção - Eletricista | F80: 838.10469 | G80: 0.15 | H80: =$D$11 -> 100 | I80: =ROUNDUP(G80*H80,0) -> 15 | J80: =F80*I80 -> 12571.57 | L80: Planilha HH
A81: 3.8 | B81: Equipe 01 (Sondador, Torrista, Plataformista, Auxiliar de Plataformista) | F81: 1684.8461 | G81: 1 | H81: =$D$11 -> 100 | I81: =ROUNDUP(G81*H81,0) -> 100 | J81: =F81*I81 -> 168484.61 | L81: Planilha HH
A82: 3.9 | B82: Equipe 02 (Sondador, Torrista, Plataformista, Auxiliar de Plataformista) | F82: =F81 -> 1684.8461 | G82: 1 | H82: =$D$11 -> 100 | I82: =ROUNDUP(G82*H82,0) -> 100 | J82: =F82*I82 -> 168484.61 | L82: Planilha HH
A83: 3.10 | B83: Equipe 03 (Sondador, Torrista, Plataformista, Auxiliar de Plataformista) | F83: =F81 -> 1684.8461 | G83: 1 | H83: =$D$11 -> 100 | I83: =ROUNDUP(G83*H83,0) -> 100 | J83: =F83*I83 -> 168484.61 | L83: Planilha HH
A84: 3.11 | B84: Equipe 04 (Sondador, Torrista, Plataformista, Auxiliar de Plataformista) | F84: =F81 -> 1684.8461 | G84: 0 | H84: =$D$11 -> 100 | I84: =ROUNDUP(G84*H84,0) -> 0 | J84: =F84*I84 -> 0 | L84: Planilha HH | M84: Caso seja necessário trabalhar CLT (Raízen), incluir a quarta equipe.
A85: SUBTOTAL | B85: SUBTOTAL MÃO DE OBRA | J85: =SUM(J76:J84) -> 724729.21
A87: ITEM | B87: 4. ALIMENTAÇÃO E HOSPEDAGEM | L87: FONTE | M87: NOTAS
B88: DESCRIÇÃO | D88: Nº de equipes | E88: Nº/equipe | F88: Total de diárias | H88: Diária (R$) | J88: Custo Total
A89: 4.1 | B89: Alimentação Equipe | D89: 2 | E89: 4 | F89: =D89*E89*D11 -> 800 | H89: 110 | J89: =F89*H89 -> 88000 | L89: Facilities
A90: 4.2 | B90: Hospedagem Equipe (quartos duplos) | D90: 2 | E90: 4 | F90: =(D90*E90*D11)/2 -> 400 | H90: 270 | J90: =F90*H90 -> 108000 | L90: Facilities
A91: 4.3 | B91: Alimentação Profissionais de Apoio (Geólogo, Tec. Segurança, Supervisor) | F91: =I76+I77+I79+I80+I78 -> 275 | H91: 38 | J91: =F91*H91 -> 10450 | L91: Facilities
A92: 4.4 | B92: Hospedagem Profissionais de Apoio (Geólogo, Tec. Segurança, Supervisor) | F92: =I76+I77+I79+I80+I78 -> 275 | H92: 270 | J92: =F92*H92 -> 74250 | L92: Facilities
A93: 4.5 | B93: Água para a equipe | F93: =D11*D89 -> 200 | H93: 12 | J93: =F93*H93 -> 2400 | L93: Facilities
A94: SUBTOTAL | B94: SUBTOTAL ALIMENTAÇÃO E HOSPEDAGEM | J94: =SUM(J89:J93) -> 283100
A96: ITEM | B96: 5. DEPRECIAÇÃO - FERRAMENTAS | L96: FONTE | M96: NOTAS
B97: Material | C97: Tipo de Formação | D97: Metragem Inicial | E97: Metragem Final | F97: Metragem Total | G97: Vida Útil (m) | H97: Valor Peça | I97: Custo Metro (R$/m) | J97: Custo Total
A98: 5.1 | B98: Broca de 17 1/2" Dente | C98: Solo/sedimento | D98: =E$18 -> 0 | E98: =F$18 -> 11.5 | F98: =E98-D98 -> 11.5 | G98: 300 | H98: 35000 | I98: =H98/G98 -> 116.66667 | J98: =F98*I98 -> 1341.6667 | L98: Valor Base
A99: 5.2 | B99: Alargador de 17 1/2" x 26" | C99: Solo/sedimento | D99: =E$18 -> 0 | E99: =F$18 -> 11.5 | F99: =E99-D99 -> 11.5 | G99: 300 | H99: 25000 | I99: =H99/G99 -> 83.333333 | J99: =F99*I99 -> 958.33333 | L99: Valor Base
A100: 5.3 | B100: Martelo Numa - 12" | C100: Basalto | D100: =E21 -> 11.5 | E100: =F21 -> 150 | F100: =E100-D100 -> 138.5 | G100: 2000 | H100: 58380 | I100: =H100/G100 -> 29.19 | J100: =F100*I100 -> 4042.815 | L100: Valor Base
A101: 5.4 | B101: Bit Numa - 18" | C101: Basalto | D101: =E21 -> 11.5 | E101: =F21 -> 150 | F101: =E101-D101 -> 138.5 | G101: 300 | H101: 50000 | I101: =H101/G101 -> 166.66667 | J101: =F101*I101 -> 23083.333 | L101: Valor Base
A102: 5.5 | B102: Broca Tricônica Botão 17 1/2" Nova | C102: Basalto | D102: =E23 -> 150 | E102: =F23 -> 400 | F102: =E102-D102 -> 250 | G102: 300 | H102: 65000 | I102: =H102/G102 -> 216.66667 | J102: =F102*I102 -> 54166.667 | L102: Valor Base
A103: 5.5 | B103: Broca Tricônica Botão 17 1/2" Nova | C103: Basalto | D103: =E24 -> 400 | E103: =F24 -> 750 | F103: =E103-D103 -> 350 | G103: 300 | H103: 65000 | I103: =H103/G103 -> 216.66667 | J103: =F103*I103 -> 75833.333 | L103: Valor Base
A104: 5.6 | B104: Broca Tricônica Dente 17 1/2" Nova | C104: Sedimento | D104: =E26 -> 750 | E104: =F26 -> 870 | F104: =E104-D104 -> 120 | G104: 300 | H104: 35000 | I104: =H104/G104 -> 116.66667 | J104: =F104*I104 -> 14000 | L104: Valor Base
A105: 5.7 | B105: Underreamer 20" - Reabertura | C105: Sedimento | D105: =E29 -> 750 | E105: =F29 -> 870 | F105: =E105-D105 -> 120 | G105: 300 | H105: 30000 | I105: =H105/G105 -> 100 | J105: =F105*I105 -> 12000 | L105: Valor Base
A106: SUBTOTAL | B106: SUBTOTAL DEPRECIAÇÃO FERRAMENTAS | J106: =SUM(J98:J105) -> 185426.15
A108: ITEM | B108: 6. DEPRECIAÇÃO - EQUIPAMENTOS/BROCAS/BITS/ALARGADORES
B109: Equipamento | F109: Unidade da Depreciação | G109: Valor | H109: Custo/unidade de depreciação | I109: Quantitadade a Depreciar | J109: Custo Total
...

Sheet Perfil Master
B2: TABELA DE PREÇOS (2025)
B3: PERFIL MASTER
A7: Cliente: | B7: ='Perfuração Cardwell'!$D$7 -> SANEPAR
A8: Metragem Poço: | B8: ='Perfuração Cardwell'!$G$7 -> 870
A9: Deslocamento (Araraquara x Obra): | B9: ='Perfuração Cardwell'!J9 -> 337 | E9: =2200 -> 2200
A11: PARÂMETROS | B11: UNIDADE | C11: VALOR UNITÁRIO | D11: QUANTIDADE | E11: VALOR | F11: NOTAS
A12: Metragem Investigada | B12: m | C12: 18.5 | D12: =$B$8 -> 870 | E12: =$C$12*$D$12 -> 16095 | F12: Metragem do poço
A13: Deslocamento | B13: km | C13: 3.5 | D13: =$B$9*2 -> 674 | E13: =$C$13*$D$13 -> 2359 | F13: Deslocamento de Araraquara à obra (ida e volta)
A14: Relatório | B14: vb | C14: 650 | D14: 1 | E14: =$C$14*$D$14 -> 650 | F14: Sempre considerar o relatório, relativo a interpretação da Perfilagem Óptica
A15: Disponibilidade | B15: dia | C15: 1000 | D15: 1 | E15: =C15*D15 -> 1000
A16: Disponibilidade | B16: dia | C16: 2700 | D16: 1 | E16: =$C$16*$D$16 -> 2700 | F16: Adequar a quantidade de acordo com a integração do cliente (duração)
A17: Multi-Função | B17: m | C17: 18.5 | D17: =$B$8 -> 870 | E17: =$C$17*$D$17 -> 16095
A18: Cáliper | B18: m | C18: 16 | D18: =$B$8 -> 870 | E18: =$C$18*$D$18 -> 13920 | F18: Considerar quando houver reabertura do poço
A19: Sônico | B19: m | C19: 18.5 | D19: =$B$8 -> 870 | E19: =$C$19*$D$19 -> 16095
A20: FlowMeter | B20: m | C20: 18.5 | D20: =$B$8 -> 870 | E20: =$C$20*$D$20 -> 16095
A21: Interpretação dos Perfis | B21: m | C21: 8 | D21: =$B$8 -> 870 | E21: =$C$21*$D$21 -> 6960
A22: Inclinação com Tropari | B22: m | C22: 350 | D22: =$B$8/100 -> 8.7 | E22: =$C$22*$D$22 -> 3045 | F22: A cada 100m, considera-se uma quantidade
D23: PERFILAGEM ÓPTICA | E23: =SUM($E$12:$E$15)/$B$8 -> 23.108046
D24: PERFILAGEM GEOFÍSICA (CÁLIPER + INCLINAÇÃO) | E24: =SUM($E$18,$E$21,$E$22,$E$16,$E$13)/$B$8 -> 33.314943
D25: PERFILAGEM GEOFÍSICA (MULTI-FUNÇÃO + SÔNICO) | E25: =SUM($E$17,$E$19,$E$16,$E$13)/$B$8 -> 42.814943

Sheet Olho no Poço
B1: PLANILHA BASE PARCEIROS 2025
B3: OLHO NO POÇO PERFILAGEM ÓTICA E DIAGNÓSTICOS DE POÇOS ARTESIANOS LTDA
B4: Rua Dr Gualter Nunes, Nº 154
B5: Bairro: Chacara Junqueira, Tatuí-SP
B6: CEP 18.271-580
B8: NOME DO CLIENTE | C8: DH Perfurações | E8: DATA DO PEDIDO | F8: NÚMERO DO PEDIDO
B9: TELEFONE CLIENTE
B10: E-MAIL DO CLIENTE | E10: DATA DE INÍCIO ESPERADA | F10: DATA DE TÉRMINO ESPERADA
B11: LOCAL DE TRABALHO
B13: DESCRIÇÃO DO TRABALHO | D13: QUANTIDADE | E13: VALOR | F13: TOTAL
B14: KM rodado (considerando saida de Tatuí/ SP) | D14: 0 | E14: $2.35 | F14: $-
B15: Perfilagem Ótica até 400 m (Valor unitário por metro) | D15: 0 | E15: $13.00 | F15: $-
B16: Perfilagem Ótica de 400 a 600 m (Valor unitário por metro) | E16: $19.50
B17: Relatório simplificado c/ imagens e posições (até 300 metros) | E17: $600.00 | F17: $-
B18: Relatório simplificado c/ imagens e posições (300 à 400 metros) | E18: $900.00 | F18: $-
B19: Relatório simplificado c/ imagens e posições (400 à 600 metros) | E19: $1,200.00 | F19: $-
B20: Relatório detalhado c/ avaliação estrutural (até 400 metros) | D20: 0 | E20: $1,900.00 | F20: $-
B21: Relatório detalhado c/ avaliação estrutural (400 à 600 metros) | E21: $2,100.00 | F21: $-
B22: Diária (disponibilidade para dia trabalhado) | D22: 0 | E22: $990.00 | F22: $-
B23: Diária (deslocamento para viagem apena. Considerar quando deslocamento total superior a 500 km) | D23: 0 | E23: $1,250.00 | F23: $-
B24: Taxa de ART | D24: 0 | E24: $120.00 | F24: $-
B25: Perfil Construtivo | D25: 0 | E25: $400.00 | F25: $-
B26: Pernoite (Considerar quando deslocamento total superior a 500 km) | D26: 0 | E26: $350.00 | F26: $-
B27: Imprevistos e Operacional | F27: $-
E28: TOTAL MÃO DE OBRA | F28: $-

Sheet Resumo
C2: CUSTEIO PERFURAÇÃO
C3: RESUMO
C4: FATURAMENTO DH
A6: LEGENDA | D6: DADOS | G6: POÇO | K6: DESLOCAMENTOS | V6: PERFURAÇÃO | W6: SERVIÇOS
B7: Células a serem preenchidas, conforme projeto/internamente | C7: Cliente: | D7: ='Perfuração Cardwell'!D7 -> SANEPAR | F7: Prof. (m) | G7: ='Perfuração Cardwell'!G7 -> 870 | K7: Campinas(km) | L7: ='Perfuração Cardwell'!J7 -> 440 | N7: PREÇO METRO (R$) | S7: 0 - NÃO | T7: 1 - SIM | V7: =SUM('Perfuração Cardwell'!J155:J159)*Resumo!S8+'Perfuração Cardwell'!J163+SUM('Perfuração Cardwell'!J139:J140) -> 60404.4 | W7: =SUM(#REF!,$J$74)*Resumo!S9 -> #REF!
B8: Responsabilidades Contratante/Contratada | C8: Município: | D8: ='Perfuração Cardwell'!D8 -> Cornélio Procópio/PR | F8: N.E. (m) | G8: ='Perfuração Cardwell'!G8 -> 0 | K8: São Paulo (km) | L8: ='Perfuração Cardwell'!J8 -> 464 | N8: ='Perfuração Cardwell'!J219 -> 7310.0505 | Q8: FAT. DIRETO | S8: 0
A9: - | B9: Itens direcionados ao Faturamento Direto/Preço de venda dos materiais | C9: Endereço: | D9: ='Perfuração Cardwell'!D9 -> Rua dos Expedicionários S/N | F9: N.D. (m) | G9: ='Perfuração Cardwell'!G9 -> 280 | K9: Araraquara (km) | L9: ='Perfuração Cardwell'!J9 -> 337 | Q9: FAT. DIRETO SERV. + MATERIAIS | S9: 0
A10: - | B10: Preço de venda do poço | F10: Q (m³/h) | G10: ='Perfuração Cardwell'!G10 -> 300 | K10: Jundiaí (km) | L10: ='Perfuração Cardwell'!J10 -> 439
F11: S (m) | G11: ='Perfuração Cardwell'!G11 -> 0
A13: ITEM | B13: 1. RESUMO
A14: 1.1 | B14: Descrição | C14: Mark-Up | D14: Preço de Venda (R$) | E14: Desconto (%) | F14: Receita Líquida (R$) | G14: Custo Total (R$) | H14: Custo M.O (R$) | I14: Depreciação Equipamentos (R$) | J14: Risco (%) | K14: Risco (R$) | L14: Margem Operacional (%) | M14: Margem líquida (%) | N14: QTD | Q14: Venda Total (R$) | R14: Receita Líquida (R$) | S14: Custo Total (R$) | T14: Custo M.O (R$) | U14: Depreciação Equipamentos (R$)
A15: 1.3 | B15: Perfuração Cardwell | C15: 1.875 | D15: ='Perfuração Cardwell'!H215 -> 6359743.9 | E15: 0.165 | F15: ='Perfuração Cardwell'!H219 -> 6000418.4 | G15: ='Perfuração Cardwell'!H221 -> 4062111.9 | H15: ='Perfuração Cardwell'!J202 -> 724729.21 | I15: ='Perfuração Cardwell'!J205 -> 62580.462 | J15: 0.15 | K15: ='Perfuração Cardwell'!J210 -> 529840.68 | L15: ='Perfuração Cardwell'!G222 -> 0.32302856 | M15: ='Perfuração Cardwell'!H229 -> 0.17302856 | N15: 1 | Q15: =D15*N15 -> 6359743.9 | R15: =F15*N15 -> 6000418.4 | S15: =G15*N15 -> 4062111.9 | T15: =H15*N15 -> 724729.21 | U15: =I15*N15 -> 62580.462
P16: TOTAL | Q16: =SUM(Q15:Q15) -> 6359743.9 | R16: =SUM(R15:R15) -> 6000418.4 | S16: =SUM(S15:S15) -> 4062111.9 | T16: =SUM(T15:T15) -> 724729.21 | U16: =SUM(U15:U15) -> 62580.462
A17: RESULTADO GERAL
A18: 1 | B18: FATOR DE VENDA | M18: FAT. DIRETO | N18: TOTAL PROPOSTA
A19: 2 | B19: PREÇO DE VENDA | K19: =Q16 -> 6359743.9 | M19: ='Perfuração Cardwell'!I215 -> 0 | N19: =K19 -> 6359743.9
A20: 3 | B20: IMPOSTOS (PIS+COFINS) | K20: =$K19*J20 -> 0
A21: 4 | B21: IMPOSTOS (ISS) - Variável | K21: =$K19*J21 -> 0 | M21: Valor de referência | N21: 7620820
A22: 5 | B22: VENDA LÍQUIDA | K22: =R16 -> 6000418.4
A23: 6 | B23: COMISSÃO | K23: =$K19*J23 -> 0 | Q23: ISS Adotado | R23: 0.02
A24: 7 | B24: CUSTO TOTAL (IMPOSTOS + CUSTO OPERACIONAL + COMISSÃO) | K24: =S16+K23 -> 4062111.9 | Q24: BASE DE CÁLCULO REDUZIDA | R24: =K19-SUM('Perfuração Cardwell'!J140,'Perfuração Cardwell'!J139,'Perfuração Cardwell'!J155:J159,'Perfuração Cardwell'!J163) -> 5395862
A25: 8 | B25: LUCRO OPERACIONAL | J25: =K25/K22 -> 0.32302856 | K25: =K22-K24 -> 1938306.5 | Q25: TOTAL ISS REDUZIDO | R25: =R23*R24 -> 107917.24
A26: 9 | B26: ADMINISTRAÇÃO CENTRAL | J26: 0.15 | K26: =$K22*J26 -> 900062.76 | Q26: ECONOMIA TOTAL | R26: =K19*R23-R25 -> 19277.639
A27: 10 | B27: MARGEM BRUTA DE CONTRIBUIÇÃO | J27: =K27/K22 -> 0.17302856 | K27: =K25-K26 -> 1038243.7 | Q27: % SOBRE RECEITA LIQUIDA | R27: =R26/K19 -> 0.0030311973
A28: 11 | B28: IMPOSTOS (IRPJ) 25% | K28: =$K27*J28 -> 0 | Q28: LUCRO LÍQUIDO + ECONOMIA | R28: =K31+R26 -> 1057521.4
A29: 12 | B29: IMPOSTOS (CSLL) 9% | K29: =$K27*J29 -> 0 | Q29: % LUCRO LÍQUIDO | R29: =R28/K22 -> 0.17624127
A30: 13 | B30: CUSTO FINANCEIRO - BASE 1% ao mês | K30: =$K19*J30 -> 0
A31: 14 | B31: LUCRO LÍQUIDO | K31: =K27-SUM(K28:K30) -> 1038243.7
B32: RESULTADO | K32: =K31/K22 -> 0.17302856

Sheet Rascunho
C23: Solicitado a Núbia confirmar na prefeitura a aliquota para o código 7.02
